asset_db/__init__.py
asset_db/repository/repository.py
asset_db/repository/repository_type.py
asset_db/repository/neo4j/__init__.py
asset_db/repository/neo4j/edge.py
asset_db/repository/neo4j/edge_tag.py
asset_db/repository/neo4j/entity.py
asset_db/repository/neo4j/entity_tag.py
asset_db/repository/neo4j/neo_repository.py
asset_db/types/__init__.py
asset_db/types/edge.py
asset_db/types/edge_tag.py
asset_db/types/entity.py
asset_db/types/entity_tag.py
asset_db-0.0.3.dist-info/METADATA
asset_db-0.0.3.dist-info/WHEEL
asset_db-0.0.3.dist-info/licenses/LICENSE
asset_db-0.0.3.dist-info/RECORD
