Metadata-Version: 2.4
Name: asset-db
Version: 0.0.3
Summary: A Python implementation of the asset Database.
Project-URL: Homepage, https://github.com/0ppliger/asset-db.py
Project-URL: Issues, https://github.com/0ppliger/asset-db.py/issues
Author-email: "J. Oppliger" <julien@oppliger.cc>
License-Expression: Apache-2.0
License-File: LICENSE
Classifier: Operating System :: OS Independent
Classifier: Programming Language :: Python :: 3
Requires-Python: >=3.10
Requires-Dist: neo4j>=6.0.3
Requires-Dist: open-asset-model>=1.0.0
